rgws/__init__.py
rgws/interface.py
rgws-0.1.5.dist-info/METADATA
rgws-0.1.5.dist-info/WHEEL
rgws-0.1.5.dist-info/top_level.txt
rgws-0.1.5.dist-info/RECORD
